ulite/__init__.py
ulite/__main__.py
ulite/version.py
ulite/backends/flask/__init__.py
ulite/backends/flask/flask_element.py
ulite/backends/flask/flask_ui.py
ulite/backends/flask/static/favicon.ico
ulite/backends/flask/static/pure-min.css
ulite/backends/flask/static/pure.css_LICENSE
ulite/backends/flask/static/ui_style.css
ulite/backends/flask/static/webui.js
ulite/backends/flask/static/fontawesome_v6_7_2_min/LICENSE.txt
ulite/backends/flask/static/fontawesome_v6_7_2_min/css/all.min.css
ulite/backends/flask/static/fontawesome_v6_7_2_min/css/fontawesome.min.css
ulite/backends/flask/static/fontawesome_v6_7_2_min/webfonts/fa-brands-400.woff2
ulite/backends/flask/static/fontawesome_v6_7_2_min/webfonts/fa-regular-400.woff2
ulite/backends/flask/static/fontawesome_v6_7_2_min/webfonts/fa-solid-900.woff2
ulite/backends/flask/static/fontawesome_v6_7_2_min/webfonts/fa-v4compatibility.woff2
ulite/backends/flask/templates/flask_index.html
ulite/core/element.py
ulite/core/event.py
ulite/core/ui.py
ulite-1.0.2.dist-info/licenses/LICENSE
ulite-1.0.2.dist-info/METADATA
ulite-1.0.2.dist-info/WHEEL
ulite-1.0.2.dist-info/top_level.txt
ulite-1.0.2.dist-info/RECORD
