Metadata-Version: 2.4
Name: ulite
Version: 1.0.2
Summary: Lightweight GUI module
Author-email: zlols <zlols@foxmail.com>
License-Expression: MIT
Project-URL: Repository, https://gitee.com/zlols/ulite.py.git
Classifier: Programming Language :: Python :: 3 :: Only
Requires-Python: >=3.8
License-File: LICENSE
Requires-Dist: Flask>=2.0.0
Requires-Dist: zlutils>=1.0.2
Dynamic: license-file
